MANIFEST.in
portal_anonymous_data.xml
setup.py
./__init__.py
./__openerp__.py
i18n/ar.po
i18n/cs.po
i18n/da.po
i18n/de.po
i18n/en_AU.po
i18n/en_GB.po
i18n/es.po
i18n/fi.po
i18n/fr.po
i18n/gl.po
i18n/hr.po
i18n/hu.po
i18n/lt.po
i18n/mk.po
i18n/mn.po
i18n/nl.po
i18n/pl.po
i18n/portal_anonymous.pot
i18n/pt.po
i18n/pt_BR.po
i18n/ro.po
i18n/ru.po
i18n/sl.po
i18n/sv.po
i18n/th.po
i18n/tr.po
i18n/zh_CN.po
openerp_portal_anonymous.egg-info/PKG-INFO
openerp_portal_anonymous.egg-info/SOURCES.txt
openerp_portal_anonymous.egg-info/dependency_links.txt
openerp_portal_anonymous.egg-info/requires.txt
openerp_portal_anonymous.egg-info/top_level.txt
security/ir.model.access.csv
static/src/js/portal_anonymous.js
static/src/xml/portal_anonymous.xml